{
  "file": "febbre.mp4",
  "lines": [
    "Ti sei preso una parte di me",
    "Quella ancora più in fondo dell’anima",
    "Un sentimento",
    "Che se si rompe taglia",
    "Come il vetro",
    "E anche deludere",
    "È un’abitudine",
    "Come nel mio primo giorno di scuola",
    "Non so che faccio qui",
    "Il buio è tagliato dalle luci viola",
    "Il cielo fa come un glitch",
    "Tu mi guardi dall’alto",
    "Trascinandomi in basso",
    "Non ascolti quando grido",
    "Sembri fatto di ghiaccio",
    "Io sono fatta così",
    "Alle feste chic",
    "Sola su un terrazzo",
    "Tutti fanno bling bling",
    "Io nemmeno mi piaccio",
    "Non dire je t’aime",
    "Dimmelo se",
    "Ciò che provi è solo febbre",
    "Che sale e scende",
    "Che mi fa male, male",
    "I tuoi occhi blu Klein",
    "Dicono che",
    "Stanotte è solo febbre",
    "Che sale e scende",
    "Tu prendi me",
    "Come un enfant per strada",
    "In abito da gala",
    "Non ci amerà la fama",
    "Non cambierà la trama",
    "Mille lune passeranno",
    "E una ci sarà per sempre",
    "Per te che non vuoi scendere",
    "Come la febbre",
    "Ti sei preso una parte di me",
    "Quella ancora più in fondo dell’anima",
    "Un sentimento",
    "Che se si rompe taglia",
    "Come il vetro",
    "Corro, corro come dentro un bosco",
    "Dentro questo inferno è più difficile",
    "Questo amore dimmi quanto costa",
    "Ti senti un’ombra qua vicino a me",
    "Non ascolti quando grido",
    "E nemmeno se taccio",
    "Non ascolti quando grido",
    "Non dire je t’aime",
    "Dimmelo se",
    "Ciò che provi è solo febbre",
    "Che sale e scende",
    "Che mi fa male, male",
    "I tuoi occhi blu Klein",
    "Dicono che",
    "Stanotte è solo febbre",
    "Che sale e scende",
    "Tu prendi me",
    "Come un enfant per strada",
    "In abito da gala",
    "Non ci amerà la fama",
    "Non cambierà la trama",
    "Mille lune passeranno",
    "E una ci sarà per sempre",
    "Per te che non vuoi scendere…",
    "Non dire je t’aime",
    "Dimmelo se",
    "Ciò che provi è solo febbre",
    "Che sale e scende",
    "Che mi fa male, male",
    "I tuoi occhi blu Klein",
    "Dicono che",
    "Stanotte è solo febbre",
    "Che poi ti prende…",
    "Come la febbre",
    "Come un enfant per strada",
    "In abito da gala",
    "Non ci amerà la fama",
    "Non cambierà la trama",
    "Mille lune passeranno",
    "E una ci sarà per sempre",
    "Per te che non vuoi scendere",
    "Come la febbre"
  ],
  "segments": [
    {
      "start": 7.96,
      "end": 12.97,
      "learned": false
    },
    {
      "start": 13.3,
      "end": 16.69,
      "learned": false
    },
    {
      "start": 16.69,
      "end": 18.3,
      "learned": false
    },
    {
      "start": 18.25,
      "end": 20.73,
      "learned": false
    },
    {
      "start": 20.85,
      "end": 22.1,
      "learned": false
    },
    {
      "start": 22.1,
      "end": 25.8,
      "learned": false
    },
    {
      "start": 25.8,
      "end": 30.1,
      "learned": false
    },
    {
      "start": 30.1,
      "end": 32.9,
      "learned": false
    },
    {
      "start": 33,
      "end": 34.38,
      "learned": false
    },
    {
      "start": 34.36,
      "end": 36.64,
      "learned": false
    },
    {
      "start": 36.64,
      "end": 38.67,
      "learned": false
    },
    {
      "start": 38.67,
      "end": 40.42,
      "learned": false
    },
    {
      "start": 40.42,
      "end": 42.44,
      "learned": false
    },
    {
      "start": 42.44,
      "end": 44.34,
      "learned": false
    },
    {
      "start": 44.34,
      "end": 46.12,
      "learned": false
    },
    {
      "start": 46.12,
      "end": 47.31,
      "learned": false
    },
    {
      "start": 47.31,
      "end": 48.12,
      "learned": false
    },
    {
      "start": 48.12,
      "end": 49.76,
      "learned": false
    },
    {
      "start": 49.76,
      "end": 50.99,
      "learned": false
    },
    {
      "start": 50.99,
      "end": 52.64,
      "learned": false
    },
    {
      "start": 52.64,
      "end": 54.51,
      "learned": false
    },
    {
      "start": 54.51,
      "end": 55.38,
      "learned": false
    },
    {
      "start": 55.38,
      "end": 57.55,
      "learned": false
    },
    {
      "start": 57.55,
      "end": 58.83,
      "learned": false
    },
    {
      "start": 58.83,
      "end": 60.57,
      "learned": false
    },
    {
      "start": 60.57,
      "end": 61.97,
      "learned": false
    },
    {
      "start": 61.97,
      "end": 62.93,
      "learned": false
    },
    {
      "start": 62.93,
      "end": 65.05,
      "learned": false
    },
    {
      "start": 65.05,
      "end": 66.42,
      "learned": false
    },
    {
      "start": 66.42,
      "end": 67.44,
      "learned": false
    },
    {
      "start": 67.44,
      "end": 69.39,
      "learned": false
    },
    {
      "start": 69.39,
      "end": 71.12,
      "learned": false
    },
    {
      "start": 71.12,
      "end": 73.02,
      "learned": false
    },
    {
      "start": 73.02,
      "end": 75.16,
      "learned": false
    },
    {
      "start": 0,
      "end": 0,
      "learned": false
    },
    {
      "start": 0,
      "end": 0,
      "learned": false
    },
    {
      "start": 0,
      "end": 0,
      "learned": false
    },
    {
      "start": 0,
      "end": 0,
      "learned": false
    },
    {
      "start": 0,
      "end": 0,
      "learned": false
    },
    {
      "start": 0,
      "end": 0,
      "learned": false
    },
    {
      "start": 0,
      "end": 0,
      "learned": false
    },
    {
      "start": 0,
      "end": 0,
      "learned": false
    },
    {
      "start": 0,
      "end": 0,
      "learned": false
    },
    {
      "start": 0,
      "end": 0,
      "learned": false
    },
    {
      "start": 0,
      "end": 0,
      "learned": false
    },
    {
      "start": 0,
      "end": 0,
      "learned": false
    },
    {
      "start": 0,
      "end": 0,
      "learned": false
    },
    {
      "start": 0,
      "end": 0,
      "learned": false
    },
    {
      "start": 0,
      "end": 0,
      "learned": false
    },
    {
      "start": 0,
      "end": 0,
      "learned": false
    },
    {
      "start": 0,
      "end": 0,
      "learned": false
    },
    {
      "start": 0,
      "end": 0,
      "learned": false
    },
    {
      "start": 0,
      "end": 0,
      "learned": false
    },
    {
      "start": 0,
      "end": 0,
      "learned": false
    },
    {
      "start": 0,
      "end": 0,
      "learned": false
    },
    {
      "start": 0,
      "end": 0,
      "learned": false
    },
    {
      "start": 0,
      "end": 0,
      "learned": false
    },
    {
      "start": 0,
      "end": 0,
      "learned": false
    },
    {
      "start": 0,
      "end": 0,
      "learned": false
    },
    {
      "start": 0,
      "end": 0,
      "learned": false
    },
    {
      "start": 0,
      "end": 0,
      "learned": false
    },
    {
      "start": 0,
      "end": 0,
      "learned": false
    },
    {
      "start": 0,
      "end": 0,
      "learned": false
    },
    {
      "start": 0,
      "end": 0,
      "learned": false
    },
    {
      "start": 0,
      "end": 0,
      "learned": false
    },
    {
      "start": 0,
      "end": 0,
      "learned": false
    },
    {
      "start": 0,
      "end": 0,
      "learned": false
    },
    {
      "start": 0,
      "end": 0,
      "learned": false
    },
    {
      "start": 0,
      "end": 0,
      "learned": false
    },
    {
      "start": 0,
      "end": 0,
      "learned": false
    },
    {
      "start": 0,
      "end": 0,
      "learned": false
    },
    {
      "start": 0,
      "end": 0,
      "learned": false
    },
    {
      "start": 0,
      "end": 0,
      "learned": false
    },
    {
      "start": 0,
      "end": 0,
      "learned": false
    },
    {
      "start": 0,
      "end": 0,
      "learned": false
    },
    {
      "start": 0,
      "end": 0,
      "learned": false
    },
    {
      "start": 0,
      "end": 0,
      "learned": false
    },
    {
      "start": 0,
      "end": 0,
      "learned": false
    },
    {
      "start": 0,
      "end": 0,
      "learned": false
    },
    {
      "start": 0,
      "end": 0,
      "learned": false
    },
    {
      "start": 0,
      "end": 0,
      "learned": false
    },
    {
      "start": 0,
      "end": 0,
      "learned": false
    },
    {
      "start": 0,
      "end": 0,
      "learned": false
    },
    {
      "start": 0,
      "end": 0,
      "learned": false
    },
    {
      "start": 0,
      "end": 0,
      "learned": false
    }
  ]
}
