{
  "version": 1,
  "song": {
    "id": "febbre",
    "title": "Febbre",
    "artist": "Clara",
    "language": "it",
    "languageName": "Italiano",
    "hint": "Можно использовать mp3 или mp4. Положи файл рядом со страницей песни или выбери локально через «🎬 Выбрать медиа».",
    "media": {
      "src": "febbre.mp4"
    }
  },
  "ui": {
    "showTranslationByDefault": true,
    "showPhoneticByDefault": false,
    "showWhyHeardByDefault": false
  },
  "items": [
    {
      "id": "fb-001",
      "text": "Ti sei preso una parte di me",
      "translation": "Ты забрал часть меня",
      "phonetic": "",
      "why": "",
      "confidence": null,
      "start": 7.96,
      "end": 12.97,
      "learned": false
    },
    {
      "id": "fb-002",
      "text": "Quella ancora più in fondo dell’anima",
      "translation": "Ту, что ещё глубже в душе",
      "phonetic": "",
      "why": "",
      "confidence": null,
      "start": 13.3,
      "end": 16.69,
      "learned": false
    },
    {
      "id": "fb-003",
      "text": "Un sentimento",
      "translation": "Чувство",
      "phonetic": "",
      "why": "",
      "confidence": null,
      "start": 16.69,
      "end": 18.3,
      "learned": false
    },
    {
      "id": "fb-004",
      "text": "Che se si rompe taglia",
      "translation": "Которое, если ломается, режет",
      "phonetic": "",
      "why": "",
      "confidence": null,
      "start": 18.25,
      "end": 20.73,
      "learned": false
    },
    {
      "id": "fb-005",
      "text": "Come il vetro",
      "translation": "Как стекло",
      "phonetic": "",
      "why": "",
      "confidence": null,
      "start": 20.85,
      "end": 22.1,
      "learned": false
    },
    {
      "id": "fb-006",
      "text": "E anche deludere",
      "translation": "И даже разочаровывать",
      "phonetic": "",
      "why": "",
      "confidence": null,
      "start": 22.1,
      "end": 25.8,
      "learned": false
    },
    {
      "id": "fb-007",
      "text": "È un’abitudine",
      "translation": "Это привычка",
      "phonetic": "",
      "why": "",
      "confidence": null,
      "start": 25.8,
      "end": 30.1,
      "learned": false
    },
    {
      "id": "fb-008",
      "text": "Come nel mio primo giorno di scuola",
      "translation": "Как в мой первый день в школе",
      "phonetic": "",
      "why": "",
      "confidence": null,
      "start": 30.1,
      "end": 32.9,
      "learned": false
    },
    {
      "id": "fb-009",
      "text": "Non so che faccio qui",
      "translation": "Я не знаю, что делаю здесь",
      "phonetic": "",
      "why": "",
      "confidence": null,
      "start": 33,
      "end": 34.38,
      "learned": false
    },
    {
      "id": "fb-010",
      "text": "Il buio è tagliato dalle luci viola",
      "translation": "Темнота разрезана фиолетовыми огнями",
      "phonetic": "",
      "why": "",
      "confidence": null,
      "start": 34.36,
      "end": 36.64,
      "learned": false
    },
    {
      "id": "fb-011",
      "text": "Il cielo fa come un glitch",
      "translation": "Небо будто глючит",
      "phonetic": "",
      "why": "",
      "confidence": null,
      "start": 36.64,
      "end": 38.67,
      "learned": false
    },
    {
      "id": "fb-012",
      "text": "Tu mi guardi dall’alto",
      "translation": "Ты смотришь на меня сверху",
      "phonetic": "",
      "why": "",
      "confidence": null,
      "start": 38.67,
      "end": 40.42,
      "learned": false
    },
    {
      "id": "fb-013",
      "text": "Trascinandomi in basso",
      "translation": "Утаскивая меня вниз",
      "phonetic": "",
      "why": "",
      "confidence": null,
      "start": 40.42,
      "end": 42.44,
      "learned": false
    },
    {
      "id": "fb-014",
      "text": "Non ascolti quando grido",
      "translation": "Ты не слышишь, когда я кричу",
      "phonetic": "",
      "why": "",
      "confidence": null,
      "start": 42.44,
      "end": 44.34,
      "learned": false
    },
    {
      "id": "fb-015",
      "text": "Sembri fatto di ghiaccio",
      "translation": "Ты будто сделан изо льда",
      "phonetic": "",
      "why": "",
      "confidence": null,
      "start": 44.34,
      "end": 46.12,
      "learned": false
    },
    {
      "id": "fb-016",
      "text": "Io sono fatta così",
      "translation": "Я такая",
      "phonetic": "",
      "why": "",
      "confidence": null,
      "start": 46.12,
      "end": 47.31,
      "learned": false
    },
    {
      "id": "fb-017",
      "text": "Alle feste chic",
      "translation": "На гламурных вечеринках",
      "phonetic": "",
      "why": "",
      "confidence": null,
      "start": 47.31,
      "end": 48.12,
      "learned": false
    },
    {
      "id": "fb-018",
      "text": "Sola su un terrazzo",
      "translation": "Одна на террасе",
      "phonetic": "",
      "why": "",
      "confidence": null,
      "start": 48.12,
      "end": 49.76,
      "learned": false
    },
    {
      "id": "fb-019",
      "text": "Tutti fanno bling bling",
      "translation": "Все сверкают",
      "phonetic": "",
      "why": "",
      "confidence": null,
      "start": 49.76,
      "end": 50.99,
      "learned": false
    },
    {
      "id": "fb-020",
      "text": "Io nemmeno mi piaccio",
      "translation": "Мне даже я сама не нравлюсь",
      "phonetic": "",
      "why": "",
      "confidence": null,
      "start": 50.99,
      "end": 52.64,
      "learned": false
    },
    {
      "id": "fb-021",
      "text": "Non dire je t’aime",
      "translation": "Не говори «je t’aime»",
      "phonetic": "",
      "why": "",
      "confidence": null,
      "start": 52.64,
      "end": 54.51,
      "learned": false
    },
    {
      "id": "fb-022",
      "text": "Dimmelo se",
      "translation": "Скажи мне, если",
      "phonetic": "",
      "why": "",
      "confidence": null,
      "start": 54.51,
      "end": 55.38,
      "learned": false
    },
    {
      "id": "fb-023",
      "text": "Ciò che provi è solo febbre",
      "translation": "То, что ты чувствуешь — всего лишь лихорадка",
      "phonetic": "",
      "why": "",
      "confidence": null,
      "start": 55.38,
      "end": 57.55,
      "learned": false
    },
    {
      "id": "fb-024",
      "text": "Che sale e scende",
      "translation": "Которая поднимается и спадает",
      "phonetic": "",
      "why": "",
      "confidence": null,
      "start": 57.55,
      "end": 58.83,
      "learned": false
    },
    {
      "id": "fb-025",
      "text": "Che mi fa male, male",
      "translation": "Которая делает мне больно, больно",
      "phonetic": "",
      "why": "",
      "confidence": null,
      "start": 58.83,
      "end": 60.57,
      "learned": false
    },
    {
      "id": "fb-026",
      "text": "I tuoi occhi blu Klein",
      "translation": "Твои синие глаза Кляйна",
      "phonetic": "",
      "why": "",
      "confidence": null,
      "start": 60.57,
      "end": 61.97,
      "learned": false
    },
    {
      "id": "fb-027",
      "text": "Dicono che",
      "translation": "Говорят, что",
      "phonetic": "",
      "why": "",
      "confidence": null,
      "start": 61.97,
      "end": 62.93,
      "learned": false
    },
    {
      "id": "fb-028",
      "text": "Stanotte è solo febbre",
      "translation": "Этой ночью — всего лишь лихорадка",
      "phonetic": "",
      "why": "",
      "confidence": null,
      "start": 62.93,
      "end": 65.05,
      "learned": false
    },
    {
      "id": "fb-029",
      "text": "Che sale e scende",
      "translation": "Которая поднимается и спадает",
      "phonetic": "",
      "why": "",
      "confidence": null,
      "start": 65.05,
      "end": 66.42,
      "learned": false
    },
    {
      "id": "fb-030",
      "text": "Tu prendi me",
      "translation": "Ты берёшь меня",
      "phonetic": "",
      "why": "",
      "confidence": null,
      "start": 66.42,
      "end": 67.44,
      "learned": false
    },
    {
      "id": "fb-031",
      "text": "Come un enfant per strada",
      "translation": "Как ребёнок на улице",
      "phonetic": "",
      "why": "",
      "confidence": null,
      "start": 67.44,
      "end": 69.39,
      "learned": false
    },
    {
      "id": "fb-032",
      "text": "In abito da gala",
      "translation": "В вечернем платье",
      "phonetic": "",
      "why": "",
      "confidence": null,
      "start": 69.39,
      "end": 71.12,
      "learned": false
    },
    {
      "id": "fb-033",
      "text": "Non ci amerà la fama",
      "translation": "Слава нас не полюбит",
      "phonetic": "",
      "why": "",
      "confidence": null,
      "start": 71.12,
      "end": 73.02,
      "learned": false
    },
    {
      "id": "fb-034",
      "text": "Non cambierà la trama",
      "translation": "Сюжет не изменится",
      "phonetic": "",
      "why": "",
      "confidence": null,
      "start": 73.02,
      "end": 75.16,
      "learned": false
    },
    {
      "id": "fb-035",
      "text": "Mille lune passeranno",
      "translation": "Пройдут тысячи лун",
      "phonetic": "",
      "why": "",
      "confidence": null,
      "start": 75.16,
      "end": 76.65,
      "learned": false
    },
    {
      "id": "fb-036",
      "text": "E una ci sarà per sempre",
      "translation": "И одна останется навсегда",
      "phonetic": "",
      "why": "",
      "confidence": null,
      "start": 77.1,
      "end": 78.9,
      "learned": false
    },
    {
      "id": "fb-037",
      "text": "Per te che non vuoi scendere",
      "translation": "Для тебя, кто не хочет спускаться",
      "phonetic": "",
      "why": "",
      "confidence": null,
      "start": 78.9,
      "end": 81,
      "learned": false
    },
    {
      "id": "fb-038",
      "text": "Come la febbre",
      "translation": "Как лихорадка",
      "phonetic": "",
      "why": "",
      "confidence": null,
      "start": 81.5,
      "end": 83,
      "learned": false
    },
    {
      "id": "fb-039",
      "text": "Ti sei preso una parte di me",
      "translation": "Ты забрал часть меня",
      "phonetic": "",
      "why": "",
      "confidence": null,
      "start": 83,
      "end": 88,
      "learned": false
    },
    {
      "id": "fb-040",
      "text": "Quella ancora più in fondo dell’anima",
      "translation": "Ту, что ещё глубже в душе",
      "phonetic": "",
      "why": "",
      "confidence": null,
      "start": 88,
      "end": 91.5,
      "learned": false
    },
    {
      "id": "fb-041",
      "text": "Un sentimento",
      "translation": "Чувство",
      "phonetic": "",
      "why": "",
      "confidence": null,
      "start": 91.5,
      "end": 93.04,
      "learned": false
    },
    {
      "id": "fb-042",
      "text": "Che se si rompe taglia",
      "translation": "Которое, если ломается, режет",
      "phonetic": "",
      "why": "",
      "confidence": null,
      "start": 93.24,
      "end": 95.5,
      "learned": false
    },
    {
      "id": "fb-043",
      "text": "Come il vetro",
      "translation": "Как стекло",
      "phonetic": "",
      "why": "",
      "confidence": null,
      "start": 95.89,
      "end": 97.3,
      "learned": false
    },
    {
      "id": "fb-044",
      "text": "Corro, corro come dentro un bosco",
      "translation": "Я бегу, бегу, как по лесу",
      "phonetic": "",
      "why": "",
      "confidence": null,
      "start": 97.9,
      "end": 99.42,
      "learned": false
    },
    {
      "id": "fb-045",
      "text": "Dentro questo inferno è più difficile",
      "translation": "В этом аду всё сложнее",
      "phonetic": "",
      "why": "",
      "confidence": null,
      "start": 99.82,
      "end": 101.51,
      "learned": false
    },
    {
      "id": "fb-046",
      "text": "Questo amore dimmi quanto costa",
      "translation": "Скажи, сколько стоит эта любовь",
      "phonetic": "",
      "why": "",
      "confidence": null,
      "start": 102,
      "end": 103.25,
      "learned": false
    },
    {
      "id": "fb-047",
      "text": "Ti senti un’ombra qua vicino a me",
      "translation": "Ты чувствуешь себя тенью рядом со мной",
      "phonetic": "",
      "why": "",
      "confidence": null,
      "start": 103.65,
      "end": 105.5,
      "learned": false
    },
    {
      "id": "fb-048",
      "text": "Non ascolti quando grido",
      "translation": "Ты не слышишь, когда я кричу",
      "phonetic": "",
      "why": "",
      "confidence": null,
      "start": 106.1,
      "end": 107.9,
      "learned": false
    },
    {
      "id": "fb-049",
      "text": "E nemmeno se taccio",
      "translation": "Даже когда я молчу",
      "phonetic": "",
      "why": "",
      "confidence": null,
      "start": 108.15,
      "end": 109.3,
      "learned": true
    },
    {
      "id": "fb-050",
      "text": "Non ascolti quando grido",
      "translation": "Ты не слышишь, когда я кричу",
      "phonetic": "",
      "why": "",
      "confidence": null,
      "start": 109.6,
      "end": 111.45,
      "learned": false
    },
    {
      "id": "fb-051",
      "text": "Non dire je t’aime",
      "translation": "Не говори «je t’aime»",
      "phonetic": "",
      "why": "",
      "confidence": null,
      "start": 112.85,
      "end": 114.24,
      "learned": false
    },
    {
      "id": "fb-052",
      "text": "Dimmelo se",
      "translation": "Скажи мне, если",
      "phonetic": "",
      "why": "",
      "confidence": null,
      "start": 114.57,
      "end": 115,
      "learned": false
    },
    {
      "id": "fb-053",
      "text": "Ciò che provi è solo febbre",
      "translation": "То, что ты чувствуешь — всего лишь лихорадка",
      "phonetic": "",
      "why": "",
      "confidence": null,
      "start": 115.4,
      "end": 117.22,
      "learned": false
    },
    {
      "id": "fb-054",
      "text": "Che sale e scende",
      "translation": "Которая поднимается и спадает",
      "phonetic": "",
      "why": "",
      "confidence": null,
      "start": 117.65,
      "end": 118.65,
      "learned": false
    },
    {
      "id": "fb-055",
      "text": "Che mi fa male, male",
      "translation": "Которая делает мне больно, больно",
      "phonetic": "",
      "why": "",
      "confidence": null,
      "start": 119.1,
      "end": 120.31,
      "learned": false
    },
    {
      "id": "fb-056",
      "text": "I tuoi occhi blu Klein",
      "translation": "Твои синие глаза Кляйна",
      "phonetic": "",
      "why": "",
      "confidence": null,
      "start": 120.61,
      "end": 121.6,
      "learned": false
    },
    {
      "id": "fb-057",
      "text": "Dicono che",
      "translation": "Говорят, что",
      "phonetic": "",
      "why": "",
      "confidence": null,
      "start": 121.89,
      "end": 122.59,
      "learned": false
    },
    {
      "id": "fb-058",
      "text": "Stanotte è solo febbre",
      "translation": "Этой ночью — всего лишь лихорадка",
      "phonetic": "",
      "why": "",
      "confidence": null,
      "start": 122.92,
      "end": 124.71,
      "learned": false
    },
    {
      "id": "fb-059",
      "text": "Che sale e scende",
      "translation": "Которая поднимается и спадает",
      "phonetic": "",
      "why": "",
      "confidence": null,
      "start": 125.2,
      "end": 126.1,
      "learned": false
    },
    {
      "id": "fb-060",
      "text": "Tu prendi me",
      "translation": "Ты берёшь меня",
      "phonetic": "",
      "why": "",
      "confidence": null,
      "start": 126.6,
      "end": 127.07,
      "learned": false
    },
    {
      "id": "fb-061",
      "text": "Come un enfant per strada",
      "translation": "Как ребёнок на улице",
      "phonetic": "",
      "why": "",
      "confidence": null,
      "start": 127.07,
      "end": 129,
      "learned": false
    },
    {
      "id": "fb-062",
      "text": "In abito da gala",
      "translation": "В вечернем платье",
      "phonetic": "",
      "why": "",
      "confidence": null,
      "start": 129.2,
      "end": 130.9,
      "learned": false
    },
    {
      "id": "fb-063",
      "text": "Non ci amerà la fama",
      "translation": "Слава нас не полюбит",
      "phonetic": "",
      "why": "",
      "confidence": null,
      "start": 131.1,
      "end": 132.7,
      "learned": false
    },
    {
      "id": "fb-064",
      "text": "Non cambierà la trama",
      "translation": "Сюжет не изменится",
      "phonetic": "",
      "why": "",
      "confidence": null,
      "start": 133,
      "end": 134.9,
      "learned": false
    },
    {
      "id": "fb-065",
      "text": "Mille lune passeranno",
      "translation": "Пройдут тысячи лун",
      "phonetic": "",
      "why": "",
      "confidence": null,
      "start": 135,
      "end": 136.7,
      "learned": false
    },
    {
      "id": "fb-066",
      "text": "E una ci sarà per sempre",
      "translation": "И одна останется навсегда",
      "phonetic": "",
      "why": "",
      "confidence": null,
      "start": 136.95,
      "end": 138.8,
      "learned": false
    },
    {
      "id": "fb-067",
      "text": "Per te che non vuoi scendere…",
      "translation": "Для тебя, кто не хочет спускаться…",
      "phonetic": "",
      "why": "",
      "confidence": null,
      "start": 139,
      "end": 142.9,
      "learned": false
    },
    {
      "id": "fb-068",
      "text": "Non dire je t’aime",
      "translation": "Не говори «je t’aime»",
      "phonetic": "",
      "why": "",
      "confidence": null,
      "start": 158,
      "end": 159.3,
      "learned": false
    },
    {
      "id": "fb-069",
      "text": "Dimmelo se",
      "translation": "Скажи мне, если",
      "phonetic": "",
      "why": "",
      "confidence": null,
      "start": 159.6,
      "end": 160.2,
      "learned": false
    },
    {
      "id": "fb-070",
      "text": "Ciò che provi è solo febbre",
      "translation": "То, что ты чувствуешь — всего лишь лихорадка",
      "phonetic": "",
      "why": "",
      "confidence": null,
      "start": 160.5,
      "end": 162.4,
      "learned": false
    },
    {
      "id": "fb-071",
      "text": "Che sale e scende",
      "translation": "Которая поднимается и спадает",
      "phonetic": "",
      "why": "",
      "confidence": null,
      "start": 162.75,
      "end": 163.7,
      "learned": false
    },
    {
      "id": "fb-072",
      "text": "Che mi fa male, male",
      "translation": "Которая делает мне больно, больно",
      "phonetic": "",
      "why": "",
      "confidence": null,
      "start": 164.2,
      "end": 165.4,
      "learned": false
    },
    {
      "id": "fb-073",
      "text": "I tuoi occhi blu Klein",
      "translation": "Твои синие глаза Кляйна",
      "phonetic": "",
      "why": "",
      "confidence": null,
      "start": 165.7,
      "end": 166.6,
      "learned": false
    },
    {
      "id": "fb-074",
      "text": "Dicono che",
      "translation": "Говорят, что",
      "phonetic": "",
      "why": "",
      "confidence": null,
      "start": 167.2,
      "end": 167.8,
      "learned": false
    },
    {
      "id": "fb-075",
      "text": "Stanotte è solo febbre",
      "translation": "Этой ночью — всего лишь лихорадка",
      "phonetic": "",
      "why": "",
      "confidence": null,
      "start": 168,
      "end": 169.9,
      "learned": false
    },
    {
      "id": "fb-076",
      "text": "Che poi ti prende…",
      "translation": "Которая потом захватывает тебя…",
      "phonetic": "",
      "why": "",
      "confidence": null,
      "start": 170.2,
      "end": 171.5,
      "learned": false
    },
    {
      "id": "fb-077",
      "text": "Come la febbre",
      "translation": "Как лихорадка",
      "phonetic": "",
      "why": "",
      "confidence": null,
      "start": 172.35,
      "end": 173.5,
      "learned": false
    },
    {
      "id": "fb-078",
      "text": "Come un enfant per strada",
      "translation": "Как ребёнок на улице",
      "phonetic": "",
      "why": "",
      "confidence": null,
      "start": 174,
      "end": 176,
      "learned": false
    },
    {
      "id": "fb-079",
      "text": "In abito da gala",
      "translation": "В вечернем платье",
      "phonetic": "",
      "why": "",
      "confidence": null,
      "start": 176.1,
      "end": 177.9,
      "learned": false
    },
    {
      "id": "fb-080",
      "text": "Non ci amerà la fama",
      "translation": "Слава нас не полюбит",
      "phonetic": "",
      "why": "",
      "confidence": null,
      "start": 177.9,
      "end": 179.9,
      "learned": false
    },
    {
      "id": "fb-081",
      "text": "Non cambierà la trama",
      "translation": "Сюжет не изменится",
      "phonetic": "",
      "why": "",
      "confidence": null,
      "start": 179.9,
      "end": 182,
      "learned": false
    },
    {
      "id": "fb-082",
      "text": "Mille lune passeranno",
      "translation": "Пройдут тысячи лун",
      "phonetic": "",
      "why": "",
      "confidence": null,
      "start": 182,
      "end": 183.8,
      "learned": false
    },
    {
      "id": "fb-083",
      "text": "E una ci sarà per sempre",
      "translation": "И одна останется навсегда",
      "phonetic": "",
      "why": "",
      "confidence": null,
      "start": 183.95,
      "end": 186,
      "learned": false
    },
    {
      "id": "fb-084",
      "text": "Per te che non vuoi scendere",
      "translation": "Для тебя, кто не хочет спускаться",
      "phonetic": "",
      "why": "",
      "confidence": null,
      "start": 186,
      "end": 189,
      "learned": false
    },
    {
      "id": "fb-085",
      "text": "Come la febbre",
      "translation": "Как лихорадка",
      "phonetic": "",
      "why": "",
      "confidence": null,
      "start": 189,
      "end": 192,
      "learned": false
    }
  ]
}
