{
  "version": 1,
  "song": {
    "id": "store-hav",
    "title": "Store Hav",
    "artist": "Kamilla Wigestrand",
    "language": "no",
    "languageName": "Norsk",
    "hint": "Выбери mp3 локально или загрузи с Яндекс.Диска.",
    "media": {
      "src": "store-hav.mp3",
      "yadisk": "https://disk.yandex.ru/d/P9Vu1Wg0Qoo19w"
    }
  },
  "ui": {
    "showOriginalByDefault": false,
    "showTranslationByDefault": false,
    "showPhoneticByDefault": false,
    "showWhyHeardByDefault": false
  },
  "items": [
    { "id": "sh-001", "text": "Store hav", "phonetic": "сту:рэ хав", "translation": "Большое море", "why": "«Store» поётся протяжно, o звучит как у:. «Hav» чётко — простое односложное слово.", "confidence": 0.95 },
    { "id": "sh-002", "text": "Noe er vekk", "phonetic": "нуммэ а сык'", "translation": "Что-то исчезло", "why": "«Noe er» поётся слитно, гласные растягиваются, r исчезает. «Vekk» теряет чёткий k и слышится как короткий резкий звук.", "confidence": 0.9 },
    { "id": "sh-003", "text": "Hver gang jeg våkner", "phonetic": "ва гом я вокнэ", "translation": "Каждый раз, когда я просыпаюсь", "why": "В «hver gang» r почти не слышно, a редуцируется. «Jeg» звучит как «я/йай». В «våkner» сочетание kn почти исчезает.", "confidence": 0.95 },
    { "id": "sh-004", "text": "Nå er det bare meg - her", "phonetic": "но а ре боре май / харь", "translation": "Теперь здесь только я", "why": "«Nå er det» поётся как единый поток. «Bare» легко превращается в «боре». «Meg» редуцируется до «май». «Her» часто растворяется в дыхании.", "confidence": 0.9 },
    { "id": "sh-005", "text": "Finner jeg frem", "phonetic": "фым нэ я фрем", "translation": "Я нахожу путь", "why": "g в «jeg» исчезает, nn в «finner» назализуется. «Frem» звучит чётко.", "confidence": 0.98 },
    { "id": "sh-006", "text": "Vandrer i tåke", "phonetic": "вомбрэри токе", "translation": "Брожу в тумане", "why": "«Vandrer i» — nd/dr сглаживаются, предлог «i» сливается. «Tåke» — å звучит как открытое о.", "confidence": 0.95 },
    { "id": "sh-007", "text": "Tror at jeg trenger deg - her", "phonetic": "тру: ат я трэнгэ дай / харь", "translation": "Думаю, что мне нужен ты — здесь", "why": "«Tror» растягивается. «Jeg» → «я». «Trenger» — ng назальное, er редуцируется. «Deg» → «дай». «Her» мягко уходит в дыхание.", "confidence": 0.85 },
    { "id": "sh-008", "text": "Men du er ikke her", "phonetic": "мэн ду э ик'э харь", "translation": "Но тебя здесь нет", "why": "Фраза чёткая, но «er» почти исчезает. «Ikke» — двойное k даёт резкий стоп. «Her» звучит мягко.", "confidence": 0.92 },
    { "id": "sh-009", "text": "Ikke her", "phonetic": "ик'э харь", "translation": "Не здесь", "why": "Короткий выдох. kk создаёт паузу внутри слова.", "confidence": 0.98 },
    { "id": "sh-010", "text": "Du er ikke her", "phonetic": "ду э ик'э харь", "translation": "Тебя здесь нет", "why": "«Du er» сливается. Остальное как выше.", "confidence": 0.95 },
    { "id": "sh-011", "text": "Ikke her", "phonetic": "ик'э харь", "translation": "Не здесь", "why": "Повтор. Простая, чёткая фраза.", "confidence": 0.98 },
    { "id": "sh-012", "text": "Når jeg frem til deg", "phonetic": "но: я фрэм тиль дай", "translation": "Доберусь ли я до тебя", "why": "«Når» растягивается. «Jeg» → «я». «Til» чётко. «Deg» → «дай» — типичная разговорная форма.", "confidence": 0.9 },
    { "id": "sh-013", "text": "Over store hav", "phonetic": "о:вэ сту:рэ хав", "translation": "Через большое море", "why": "«Over» — er на конце почти не слышно. «Store hav» как в припеве.", "confidence": 0.95 },
    { "id": "sh-014", "text": "Husker du det vi var", "phonetic": "хюскэ ду дэ ви ва:", "translation": "Помнишь ли ты, чем мы были", "why": "«Husker» — er проглатывается. «Det» редуцируется до «дэ». «Var» растягивается.", "confidence": 0.88 },
    { "id": "sh-015", "text": "Det vi er, og", "phonetic": "дэ ви э / о:", "translation": "То, что мы есть, и", "why": "Максимально сжатая фраза. «Det» → «дэ», «er» почти не слышно, «og» растягивается.", "confidence": 0.85 },
    { "id": "sh-016", "text": "Det du har her", "phonetic": "дэ ду ха: харь", "translation": "То, что у тебя есть здесь", "why": "«Har» и «her» похожи на слух — отличаются только гласным. Оба мягко произносятся.", "confidence": 0.88 },
    { "id": "sh-017", "text": "Når jeg frem til deg", "phonetic": "но: я фрэм тиль дай", "translation": "Доберусь ли я до тебя", "why": "Повтор припева. См. sh-012.", "confidence": 0.9 },
    { "id": "sh-018", "text": "Over store hav", "phonetic": "о:вэ сту:рэ хав", "translation": "Через большое море", "why": "Повтор. См. sh-013.", "confidence": 0.95 },
    { "id": "sh-019", "text": "Husker du det vi var", "phonetic": "хюскэ ду дэ ви ва:", "translation": "Помнишь ли ты, чем мы были", "why": "Повтор. См. sh-014.", "confidence": 0.88 },
    { "id": "sh-020", "text": "Det vi er, og", "phonetic": "дэ ви э / о:", "translation": "То, что мы есть, и", "why": "Повтор. См. sh-015.", "confidence": 0.85 },
    { "id": "sh-021", "text": "Det du har her", "phonetic": "дэ ду ха: харь", "translation": "То, что у тебя есть здесь", "why": "Повтор. См. sh-016.", "confidence": 0.88 },
    { "id": "sh-022", "text": "Jeg stod igjen", "phonetic": "яй сту: ийэн", "translation": "Я остался стоять", "why": "«Jeg» → «яй/я». «Stod» — d на конце может быть немым. «Igjen» — gj даёт мягкий й-звук.", "confidence": 0.87 },
    { "id": "sh-023", "text": "Du dro av gårde", "phonetic": "ду дру: а го:рэ", "translation": "Ты уехал", "why": "«Dro» растягивается. «Av» → «а». «Gårde» — å даёт открытое о, d может быть мягким или немым.", "confidence": 0.85 },
    { "id": "sh-024", "text": "Hva om du glemmer meg - der", "phonetic": "ва ом ду глэмэ май / дэр", "translation": "Что если ты забудешь меня — там", "why": "«Hva» — h немое. «Glemmer» — mm назализуется, er исчезает. «Meg» → «май». «Der» чётко.", "confidence": 0.87 },
    { "id": "sh-025", "text": "Dager er grå", "phonetic": "да:гэ э гро:", "translation": "Дни серые", "why": "«Dager» — er проглатывается. «Grå» — å даёт долгое открытое о.", "confidence": 0.92 },
    { "id": "sh-026", "text": "Husker du våre?", "phonetic": "хюскэ ду во:рэ", "translation": "Помнишь ли ты наши?", "why": "«Våre» — å как открытое о, re на конце мягко.", "confidence": 0.9 },
    { "id": "sh-027", "text": "Kjenner du meg igjen - her", "phonetic": "шэннэ ду май ийэн / харь", "translation": "Узнаёшь ли ты меня снова — здесь", "why": "«Kjenner» — kj даёт шипящий звук, похожий на щ/ш. «Meg» → «май». «Igjen» — мягкий й.", "confidence": 0.88 },
    { "id": "sh-028", "text": "Men du er ikke her", "phonetic": "мэн ду э ик'э харь", "translation": "Но тебя здесь нет", "why": "Повтор. См. sh-008.", "confidence": 0.92 },
    { "id": "sh-029", "text": "Ikke her", "phonetic": "ик'э харь", "translation": "Не здесь", "why": "Повтор. См. sh-009.", "confidence": 0.98 },
    { "id": "sh-030", "text": "Du er ikke her", "phonetic": "ду э ик'э харь", "translation": "Тебя здесь нет", "why": "Повтор. См. sh-010.", "confidence": 0.95 },
    { "id": "sh-031", "text": "Ikke her", "phonetic": "ик'э харь", "translation": "Не здесь", "why": "Повтор.", "confidence": 0.98 },
    { "id": "sh-032", "text": "Når jeg frem til deg", "phonetic": "но: я фрэм тиль дай", "translation": "Доберусь ли я до тебя", "why": "Повтор припева.", "confidence": 0.9 },
    { "id": "sh-033", "text": "Over store hav", "phonetic": "о:вэ сту:рэ хав", "translation": "Через большое море", "why": "Повтор.", "confidence": 0.95 },
    { "id": "sh-034", "text": "Husker du det vi var", "phonetic": "хюскэ ду дэ ви ва:", "translation": "Помнишь ли ты, чем мы были", "why": "Повтор.", "confidence": 0.88 },
    { "id": "sh-035", "text": "Det vi er, og", "phonetic": "дэ ви э / о:", "translation": "То, что мы есть, и", "why": "Повтор.", "confidence": 0.85 },
    { "id": "sh-036", "text": "Det du har her", "phonetic": "дэ ду ха: харь", "translation": "То, что у тебя есть здесь", "why": "Повтор.", "confidence": 0.88 },
    { "id": "sh-037", "text": "Når jeg frem til deg", "phonetic": "но: я фрэм тиль дай", "translation": "Доберусь ли я до тебя", "why": "Повтор.", "confidence": 0.9 },
    { "id": "sh-038", "text": "Over store hav", "phonetic": "о:вэ сту:рэ хав", "translation": "Через большое море", "why": "Повтор.", "confidence": 0.95 },
    { "id": "sh-039", "text": "Husker du det vi var", "phonetic": "хюскэ ду дэ ви ва:", "translation": "Помнишь ли ты, чем мы были", "why": "Повтор.", "confidence": 0.88 },
    { "id": "sh-040", "text": "Det vi er, og", "phonetic": "дэ ви э / о:", "translation": "То, что мы есть, и", "why": "Повтор.", "confidence": 0.85 },
    { "id": "sh-041", "text": "Det du har her", "phonetic": "дэ ду ха: харь", "translation": "То, что у тебя есть здесь", "why": "Повтор.", "confidence": 0.88 }
  ]
}
